{
  "films": [
    {
      "name": "film1",
      "release": "2001",
      "genre": "fantasy",
      "director": "Travolta",
      "starring": "blablabla",
      "id": "1"
    },
    {
      "name": "film2",
      "release": "2002",
      "genre": "fantasy",
      "director": "Travolta",
      "starring": "blablabla",
      "id": "2"
    },
    {
      "name": "film3",
      "release": "2003",
      "genre": "fantasy",
      "director": "Travolta",
      "starring": "blablabla",
      "id": "3"
    }
  ]
}
